{
  "parent": "minecraft:item/generated",
  "textures": {
    "layer0": "minecraft:item/cooked_beef"
  },
  "overrides": [
    {
      "predicate": {
        "custom_model_data": 1
      },
      "model": "core:item/foods/rice/rice_cake"
    },
    {
      "predicate": {
        "custom_model_data": 2
      },
      "model": "railway:item/foods/beef/cooked_japanese_wagyu_beef"
    },
    {
      "predicate": {
        "custom_model_data": 3
      },
      "model": "core:item/foods/choco/choco1"
    },
    {
      "predicate": {
        "custom_model_data": 4
      },
      "model": "core:item/foods/choco/choco2"
    },
    {
      "predicate": {
        "custom_model_data": 5
      },
      "model": "core:item/foods/choco/choco3"
    },
    {
      "predicate": {
        "custom_model_data": 6
      },
      "model": "core:item/foods/cake/cake"
    },
    {
      "predicate": {
        "custom_model_data": 8
      },
      "model": "core:item/foods/cake/cake2"
    }
  ]
}
