{
    "parent": "item/generated",
    "textures": {
        "layer0": "item/salmon"
    },
    "overrides": [
        {
            "predicate": {
                "custom_model_data": 1
            },
            "model": "custom/fish/outstanding_fish"
        },
        {
            "predicate": {
                "custom_model_data": 2
            },
            "model": "custom/fish/grunt_fish"
        },
        {
            "predicate": {
                "custom_model_data": 3
            },
            "model": "custom/fish/japanese_spanish_mackerel_fish"
        },
        {
            "predicate": {
                "custom_model_data": 4
            },
            "model": "custom/fish/glitter_eel_fish"
        }
    ]
}